{
  "dynamic_home_page": [
    {
      "class_name": "SensorProvider",
      "title": "Accelerometer"
    },
    {
      "class_name": "SensorProvider",
      "title": "Gyroscope"
    },
    {
      "class_name": "SensorProvider",
      "title": "Magnetometer"
    },
    {
      "class_name": "SensorProvider",
      "title": "Gravity Sensor"
    },
    {
      "class_name": "SensorProvider",
      "title": "Linear Acceleration"
    },
    {
      "class_name": "SensorProvider",
      "title": "Rotation Sensor"
    },
    {
      "class_name": "SensorProvider",
      "title": "Ambient Temperature"
    },
    {
      "class_name": "SensorProvider",
      "title": "Proximity Sensor"
    },
    {
      "class_name": "SensorProvider",
      "title": "Light Sensor"
    }
    ,{
      "class_name": "SensorProvider",
      "title": "Pressure Sensor"
    },
    {
      "class_name": "SensorProvider",
      "title": "Relative Sensor"
    }
  ]
}